scope_cleaner/__init__.py
scope_cleaner/magic.py
scope_cleaner/variable_extraction.py
scope_cleaner-0.1.0.post4.dist-info/LICENSE
scope_cleaner-0.1.0.post4.dist-info/WHEEL
scope_cleaner-0.1.0.post4.dist-info/METADATA
scope_cleaner-0.1.0.post4.dist-info/RECORD
