Metadata-Version: 2.1
Name: scope-cleaner
Version: 0.1.0.post4
Summary: An IPython cell magic to remove temporary variables
License: MIT
Author: Nikolay Chechulin
Author-email: nchechulin@protonmail.com
Requires-Python: >=3.8,<4.0
Classifier: License :: OSI Approved :: MIT License
Classifier: Programming Language :: Python :: 3
Classifier: Programming Language :: Python :: 3.8
Classifier: Programming Language :: Python :: 3.9
Classifier: Programming Language :: Python :: 3.10
Classifier: Programming Language :: Python :: 3.11
Requires-Dist: ipython (>=8.5.0,<9.0.0)
Project-URL: Bug tracker, https://github.com/NChechulin/scope-cleaner/issues
Project-URL: Homepage, https://github.com/NChechulin/scope-cleaner
